makehuman/__init__.py
makehuman/compile_models.py
makehuman/compile_proxies.py
makehuman/compile_targets.py
makehuman/create_pylint_log.py
makehuman/download_assets.py
makehuman/download_assets_git.py
makehuman/makehuman.py
makehuman/test.py
makehuman/apps/autoskinblender.py
makehuman/apps/catmull_clark_subdivision.py
makehuman/apps/compat.py
makehuman/apps/devtests.py
makehuman/apps/human.py
makehuman/apps/humanmodifier.py
makehuman/apps/metadataengine.py
makehuman/apps/warpmodifier.py
makehuman/apps/which.py
makehuman/apps/gui/guiexport.py
makehuman/apps/gui/guifiles.py
makehuman/apps/gui/guiload.py
makehuman/apps/gui/guimodifier.py
makehuman/apps/gui/guirender.py
makehuman/apps/gui/guisave.py
makehuman/apps/gui/proxychooser.py
makehuman/core/algos3d.py
makehuman/core/animation3d.py
makehuman/core/events3d.py
makehuman/core/export.py
makehuman/core/files3d.py
makehuman/core/geometry3d.py
makehuman/core/gui3d.py
makehuman/core/guicommon.py
makehuman/core/managed_file.py
makehuman/core/mhmain.py
makehuman/core/module3d.py
makehuman/core/selection.py
makehuman/core/transformations.py
makehuman/data/clear.thumb
makehuman/data/images.list
makehuman/data/logging.ini
makehuman/data/notfound.thumb
makehuman/data/targets.npz
makehuman/lib/camera.py
makehuman/lib/core.py
makehuman/lib/debugdump.py
makehuman/lib/eventqueue.py
makehuman/lib/filecache.py
makehuman/lib/filechooser.py
makehuman/lib/getpath.py
makehuman/lib/gitutils.py
makehuman/lib/glmodule.py
makehuman/lib/gui.py
makehuman/lib/humanobjchooser.py
makehuman/lib/image.py
makehuman/lib/image_qt.py
makehuman/lib/inifile.py
makehuman/lib/language.py
makehuman/lib/log.py
makehuman/lib/matrix.py
makehuman/lib/mh.py
makehuman/lib/mhversion.py
makehuman/lib/modifierslider.py
makehuman/lib/object3d.py
makehuman/lib/profiler.py
makehuman/lib/qtgui.py
makehuman/lib/qtui.py
makehuman/lib/shader.py
makehuman/lib/sorter.py
makehuman/lib/targets.py
makehuman/lib/texture.py
makehuman/lib/unique.py
makehuman/lib/xdg_parser.py
makehuman-1.3.2.dist-info/METADATA
makehuman-1.3.2.dist-info/WHEEL
makehuman-1.3.2.dist-info/entry_points.txt
makehuman-1.3.2.dist-info/top_level.txt
makehuman-1.3.2.dist-info/RECORD
